pygame_physics/__init__.py
pygame_physics-0.0.0.dist-info/METADATA
pygame_physics-0.0.0.dist-info/WHEEL
pygame_physics-0.0.0.dist-info/top_level.txt
pygame_physics-0.0.0.dist-info/RECORD
