Metadata-Version: 1.2
Name: pygame_physics
Version: 0.0.0
Summary: A way to manage physics of objects in pygame
Home-page: https://github.com/GrantGMiller/pygame_physics
Author: Grant miller
Author-email: grant@grant-miller.com
License: PSF
Project-URL: Source Code, https://github.com/GrantGMiller/pygame_physics
Keywords: grant miller pygame physics
Platform: UNKNOWN
